{"headerImage":"https:\/\/comment.sinaimg.cn\/96\/56\/7cdd187bcda4d1e99b1211f2a69e605ee241.jpg","tintColor":"#47afd1","tabs":[{"views":[{"class":"DepictionSpacerView","spacing":12},{"text":"Click here to buy me a coffee :)","yPadding":10,"action":"https:\/\/qr.alipay.com\/fkx16005vrem50fhc8jdye3","class":"DepictionButtonView"},{"class":"DepictionHeaderView","title":"Description"},{"class":"DepictionMarkdownView","markdown":"Disable AppStore app thinning - by level3tjg, TestFlight app thinning - by Netskao"},{"title":"Info","class":"DepictionHeaderView"},{"text":"1.3","class":"DepictionTableTextView","title":"Version"},{"text":"ned","class":"DepictionTableTextView","title":"Developer"},{"class":"DepictionTableButtonView","title":"Twitter","action":"https:\/\/twitter.com\/Netskao"},{"action":"https:\/\/t.me\/IPAPatch","title":"Telegram","class":"DepictionTableButtonView"}],"class":"DepictionStackView","tabname":"Details"},{"views":[{"views":[{"useBoldText":true,"class":"DepictionSubheaderView","title":"1.3","alignment":0},{"class":"DepictionSubheaderView","title":"2024-11-04","alignment":2}],"class":"DepictionLayerView"},{"markdown":"Fix TestFlight 3.6.0 failure","useSpacing":true,"class":"DepictionMarkdownView"},{"class":"DepictionSpacerView","spacing":12},{"class":"DepictionLayerView","views":[{"class":"DepictionSubheaderView","title":"1.2","alignment":0,"useBoldText":true},{"alignment":2,"title":"2024-10-20","class":"DepictionSubheaderView"}]},{"class":"DepictionMarkdownView","useSpacing":true,"markdown":"Initial update"},{"spacing":12,"class":"DepictionSpacerView"}],"class":"DepictionStackView","tabname":"Changes"}],"minVersion":"0.4","class":"DepictionTabView"}
